bomber/__init__.py
bomber/bomber.py
siampy-2.3.4.dist-info/LICENSE
siampy-2.3.4.dist-info/METADATA
siampy-2.3.4.dist-info/WHEEL
siampy-2.3.4.dist-info/top_level.txt
siampy-2.3.4.dist-info/RECORD
