Metadata-Version: 2.1
Name: siampy
Version: 2.3.4
Summary: SMS Bomber Project.
Home-page: https://github.com/siamrahman000
Author: SIAM RAHMAN
Author-email: s14mbro1@gmail.com
Project-URL: Bug Tracker, https://github.com/SIAMRAHMAN000
Classifier: Development Status :: 5 - Production/Stable
Classifier: Programming Language :: Python :: 3
Classifier: Programming Language :: Python :: 3.5
Classifier: Programming Language :: Python
Classifier: License :: OSI Approved :: MIT License
Classifier: Operating System :: OS Independent
Requires-Python: >=3.6
License-File: LICENSE
